exchangetransformrepo/ExchangeTransform.py
exchangetransformrepo/__init__.py
exchangetransformrepo/repository/ExchangeTransformRepository.py
exchangetransformrepo/repository/__init__.py
exchangetransformrepo/repository/serialize/__init__.py
exchangetransformrepo/repository/serialize/exchange_transform_deserializer.py
exchangetransformrepo/repository/serialize/exchange_transform_serializer.py
persuader_technology_automata_exchange_transform_repository-0.2.0.dist-info/LICENSE
persuader_technology_automata_exchange_transform_repository-0.2.0.dist-info/METADATA
persuader_technology_automata_exchange_transform_repository-0.2.0.dist-info/WHEEL
persuader_technology_automata_exchange_transform_repository-0.2.0.dist-info/top_level.txt
persuader_technology_automata_exchange_transform_repository-0.2.0.dist-info/RECORD
